MANIFEST.in
README.rst
setup.cfg
setup.py
collective/__init__.py
collective.unslider.egg-info/PKG-INFO
collective.unslider.egg-info/SOURCES.txt
collective.unslider.egg-info/dependency_links.txt
collective.unslider.egg-info/entry_points.txt
collective.unslider.egg-info/namespace_packages.txt
collective.unslider.egg-info/not-zip-safe
collective.unslider.egg-info/paster_plugins.txt
collective.unslider.egg-info/requires.txt
collective.unslider.egg-info/top_level.txt
collective/unslider/__init__.py
collective/unslider/configure.zcml
collective/unslider/interfaces.py
collective/unslider/setuphandlers.py
collective/unslider/behavior/README.txt
collective/unslider/behavior/__init__.py
collective/unslider/behavior/configure.zcml
collective/unslider/browser/README.txt
collective/unslider/browser/__init__.py
collective/unslider/content/README.txt
collective/unslider/content/__init__.py
collective/unslider/locales/README.txt
collective/unslider/portlet/__init__.py
collective/unslider/portlet/configure.zcml
collective/unslider/portlet/unsliderportlet.py
collective/unslider/portlet/templates/unsliderportlet.pt
collective/unslider/profiles/default/browserlayer.xml
collective/unslider/profiles/default/collective.unslider.marker.txt
collective/unslider/profiles/default/cssregistry.xml
collective/unslider/profiles/default/jsregistry.xml
collective/unslider/profiles/default/metadata.xml
collective/unslider/profiles/default/portlets.xml
collective/unslider/profiles/default/types.xml
collective/unslider/schemaextender/__init__.py
collective/unslider/static/README.txt
collective/unslider/static/unslider.css
collective/unslider/static/unslider.js
collective/unslider/upgrades/__init__.py
collective/unslider/upgrades/handlers.py
collective/unslider/upgrades/profiles.py
collective/unslider/viewlet/__init__.py
collective/unslider/vocabulary/__init__.py
docs/HISTORY.rst
docs/INSTALL.rst
docs/LICENSE.GPL
docs/LICENSE.txt